CHANGES.txt
zigzag/__init__.py
zigzag/core.cpython-38-x86_64-linux-gnu.so
zigzag/core.pyx
zigzag/plotting.py
zigzag-0.3.2.dist-info/LICENSE.txt
zigzag-0.3.2.dist-info/WHEEL
zigzag-0.3.2.dist-info/METADATA
zigzag-0.3.2.dist-info/RECORD
