Metadata-Version: 2.1
Name: zigzag
Version: 0.3.2
Summary: Package for finding peaks and valleys of time series.
Home-page: https://github.com/jbn/ZigZag
License: BSD-3-Clause
Author: generativist
Author-email: jbn@abreka.com
Requires-Python: >=3.8
Classifier: License :: OSI Approved :: BSD License
Classifier: Programming Language :: Python :: 3
Classifier: Programming Language :: Python :: 3.10
Classifier: Programming Language :: Python :: 3.8
Classifier: Programming Language :: Python :: 3.9
Requires-Dist: Cython (>=0.29,<0.30)
Requires-Dist: numpy (>=1.21.1)
Project-URL: Repository, https://github.com/jbn/ZigZag
